{"user_id":13,"product_id":16,"quantity":6,"name":"Suzanne Sweeney","email":"marknolan@example.org","date":"2021-08-17"}
{"user_id":29,"product_id":89,"quantity":9,"name":"Tara Wheeler","email":"ehunt@example.com","date":"2021-05-11"}
{"user_id":61,"product_id":8,"quantity":6,"name":"James Stevenson","email":"johnsonchristopher@example.com","date":"2021-06-25"}
{"user_id":18,"product_id":89,"quantity":6,"name":"Thomas Perez","email":"vargasmegan@example.com","date":"2020-02-05"}
{"user_id":69,"product_id":90,"quantity":8,"name":"Phillip Murphy","email":"deckereric@example.net","date":"2021-08-24"}
{"user_id":54,"product_id":82,"quantity":7,"name":"Audrey Mitchell","email":"cameron88@example.net","date":"2021-09-16"}
{"user_id":83,"product_id":23,"quantity":2,"name":"Lisa Sanders","email":"megan66@example.org","date":"2021-06-12"}
{"user_id":95,"product_id":70,"quantity":1,"name":"Chelsea Chen","email":"erinrodriguez@example.com","date":"2021-01-01"}
{"user_id":61,"product_id":33,"quantity":7,"name":"James Stevenson","email":"johnsonchristopher@example.com","date":"2021-06-25"}
{"user_id":19,"product_id":38,"quantity":5,"name":"Kathy Wilson","email":"jessica69@example.net","date":"2020-04-10"}
{"user_id":21,"product_id":10,"quantity":2,"name":"Lauren Cooper","email":"sophia06@example.net","date":"2021-02-18"}
{"user_id":42,"product_id":97,"quantity":7,"name":"Robin Carroll","email":"brettyoung@example.org","date":"2022-01-20"}
{"user_id":64,"product_id":77,"quantity":6,"name":"Elizabeth Murphy","email":"dbright@example.org","date":"2022-03-09"}
{"user_id":90,"product_id":43,"quantity":5,"name":"Stephanie Watts","email":"peter01@example.org","date":"2020-04-08"}
{"user_id":46,"product_id":49,"quantity":5,"name":"Desiree Castillo","email":"vickimorris@example.org","date":"2020-01-22"}
{"user_id":37,"product_id":90,"quantity":4,"name":"Steven Lee","email":"lisawilson@example.net","date":"2022-04-18"}
{"user_id":93,"product_id":87,"quantity":2,"name":"William Montgomery","email":"pateljoseph@example.com","date":"2021-03-23"}
{"user_id":18,"product_id":58,"quantity":5,"name":"Thomas Perez","email":"vargasmegan@example.com","date":"2020-02-05"}
{"user_id":28,"product_id":13,"quantity":8,"name":"Wesley Pearson","email":"ewallace@example.com","date":"2021-05-04"}
{"user_id":10,"product_id":19,"quantity":6,"name":"Mike Robertson III","email":"brettpierce@example.org","date":"2021-11-26"}
{"user_id":7,"product_id":84,"quantity":7,"name":"Amy Peterson","email":"jenniferbell@example.com","date":"2020-09-13"}
{"user_id":60,"product_id":41,"quantity":7,"name":"Ronald Hebert","email":"westjoshua@example.net","date":"2020-12-22"}
{"user_id":37,"product_id":12,"quantity":4,"name":"Steven Lee","email":"lisawilson@example.net","date":"2022-04-18"}
{"user_id":9,"product_id":20,"quantity":5,"name":"Jennifer Hammond","email":"lindseymays@example.com","date":"2022-07-10"}
{"user_id":24,"product_id":65,"quantity":8,"name":"Gary Henry","email":"mkidd@example.com","date":"2020-01-16"}
{"user_id":15,"product_id":57,"quantity":5,"name":"Jeff Castillo","email":"jonathanmendoza@example.com","date":"2021-04-14"}
{"user_id":38,"product_id":44,"quantity":6,"name":"Gilbert Ross","email":"jboyle@example.org","date":"2021-09-09"}
{"user_id":90,"product_id":28,"quantity":8,"name":"Stephanie Watts","email":"peter01@example.org","date":"2020-04-08"}
{"user_id":60,"product_id":63,"quantity":3,"name":"Ronald Hebert","email":"westjoshua@example.net","date":"2020-12-22"}
{"user_id":17,"product_id":19,"quantity":8,"name":"Michelle Sanders","email":"oliviaray@example.net","date":"2021-09-14"}
{"user_id":8,"product_id":2,"quantity":5,"name":"Aaron King","email":"marcusmerritt@example.org","date":"2020-02-28"}
{"user_id":12,"product_id":80,"quantity":1,"name":"Christine Riley","email":"williamsnicholas@example.com","date":"2022-09-11"}
{"user_id":78,"product_id":19,"quantity":5,"name":"Tracy Brown","email":"zcastillo@example.com","date":"2022-04-06"}
{"user_id":56,"product_id":89,"quantity":9,"name":"Tyler Odonnell","email":"jeffrey91@example.com","date":"2022-01-19"}
{"user_id":18,"product_id":31,"quantity":4,"name":"Thomas Perez","email":"vargasmegan@example.com","date":"2020-02-05"}
{"user_id":12,"product_id":15,"quantity":3,"name":"Christine Riley","email":"williamsnicholas@example.com","date":"2022-09-11"}
{"user_id":54,"product_id":26,"quantity":4,"name":"Audrey Mitchell","email":"cameron88@example.net","date":"2021-09-16"}
{"user_id":1,"product_id":88,"quantity":9,"name":"Tiffany Washington","email":"hallrichard@example.org","date":"2021-09-12"}
{"user_id":29,"product_id":83,"quantity":5,"name":"Tara Wheeler","email":"ehunt@example.com","date":"2021-05-11"}
{"user_id":91,"product_id":46,"quantity":3,"name":"Brian Taylor","email":"william03@example.net","date":"2020-10-24"}
{"user_id":100,"product_id":41,"quantity":9,"name":"Natalie Weaver","email":"colleennelson@example.net","date":"2022-08-26"}
{"user_id":24,"product_id":78,"quantity":1,"name":"Gary Henry","email":"mkidd@example.com","date":"2020-01-16"}
{"user_id":36,"product_id":73,"quantity":2,"name":"Danielle Compton","email":"lhenry@example.net","date":"2020-01-21"}
{"user_id":91,"product_id":23,"quantity":5,"name":"Brian Taylor","email":"william03@example.net","date":"2020-10-24"}
{"user_id":72,"product_id":83,"quantity":8,"name":"Donald Hernandez","email":"jeffrey38@example.org","date":"2021-05-16"}
{"user_id":99,"product_id":52,"quantity":1,"name":"James Baker","email":"heather64@example.org","date":"2022-02-13"}
{"user_id":15,"product_id":68,"quantity":2,"name":"Jeff Castillo","email":"jonathanmendoza@example.com","date":"2021-04-14"}
{"user_id":90,"product_id":34,"quantity":9,"name":"Stephanie Watts","email":"peter01@example.org","date":"2020-04-08"}
{"user_id":43,"product_id":22,"quantity":3,"name":"Stephanie Anthony","email":"sarah57@example.com","date":"2021-05-09"}
{"user_id":23,"product_id":12,"quantity":7,"name":"Matthew Walker","email":"smithkenneth@example.com","date":"2021-06-14"}
{"user_id":98,"product_id":70,"quantity":8,"name":"Daniel Stuart","email":"hopkinskaren@example.net","date":"2021-10-25"}
{"user_id":71,"product_id":51,"quantity":6,"name":"Sara Washington","email":"jennifer04@example.net","date":"2021-01-03"}
{"user_id":92,"product_id":20,"quantity":7,"name":"James Wilson","email":"sharon53@example.org","date":"2020-02-20"}
{"user_id":12,"product_id":45,"quantity":6,"name":"Christine Riley","email":"williamsnicholas@example.com","date":"2022-09-11"}
{"user_id":32,"product_id":24,"quantity":9,"name":"Daniel Ray","email":"dianeromero@example.org","date":"2020-11-22"}
{"user_id":3,"product_id":67,"quantity":5,"name":"Brian Washington","email":"justin76@example.com","date":"2020-09-15"}
{"user_id":17,"product_id":53,"quantity":5,"name":"Michelle Sanders","email":"oliviaray@example.net","date":"2021-09-14"}
{"user_id":63,"product_id":59,"quantity":5,"name":"Gregory Munoz","email":"ericwilliams@example.org","date":"2020-08-10"}
{"user_id":18,"product_id":24,"quantity":8,"name":"Thomas Perez","email":"vargasmegan@example.com","date":"2020-02-05"}
{"user_id":71,"product_id":5,"quantity":8,"name":"Sara Washington","email":"jennifer04@example.net","date":"2021-01-03"}
{"user_id":22,"product_id":14,"quantity":7,"name":"James Thomas","email":"barrygonzalez@example.net","date":"2020-12-17"}
{"user_id":67,"product_id":24,"quantity":1,"name":"Amber Jensen","email":"monicawilliams@example.com","date":"2021-05-18"}
{"user_id":15,"product_id":49,"quantity":4,"name":"Jeff Castillo","email":"jonathanmendoza@example.com","date":"2021-04-14"}
{"user_id":13,"product_id":84,"quantity":9,"name":"Suzanne Sweeney","email":"marknolan@example.org","date":"2021-08-17"}
{"user_id":93,"product_id":93,"quantity":5,"name":"William Montgomery","email":"pateljoseph@example.com","date":"2021-03-23"}
{"user_id":42,"product_id":23,"quantity":1,"name":"Robin Carroll","email":"brettyoung@example.org","date":"2022-01-20"}
{"user_id":51,"product_id":52,"quantity":8,"name":"Jason Hart","email":"seanrodriguez@example.com","date":"2021-11-14"}
{"user_id":91,"product_id":88,"quantity":3,"name":"Brian Taylor","email":"william03@example.net","date":"2020-10-24"}
{"user_id":11,"product_id":75,"quantity":4,"name":"Michael Scott","email":"emilymorgan@example.net","date":"2020-08-02"}
{"user_id":67,"product_id":87,"quantity":5,"name":"Amber Jensen","email":"monicawilliams@example.com","date":"2021-05-18"}
{"user_id":9,"product_id":12,"quantity":1,"name":"Jennifer Hammond","email":"lindseymays@example.com","date":"2022-07-10"}
{"user_id":36,"product_id":33,"quantity":8,"name":"Danielle Compton","email":"lhenry@example.net","date":"2020-01-21"}
{"user_id":84,"product_id":95,"quantity":6,"name":"Mary Arias","email":"donaldhill@example.org","date":"2022-07-10"}
{"user_id":70,"product_id":23,"quantity":4,"name":"Susan Blake","email":"gonzalezpamela@example.net","date":"2021-11-14"}
{"user_id":68,"product_id":51,"quantity":7,"name":"Dakota Ellison","email":"erin82@example.net","date":"2020-10-05"}
{"user_id":59,"product_id":42,"quantity":7,"name":"Russell Flores","email":"woodscameron@example.org","date":"2022-02-23"}
{"user_id":92,"product_id":100,"quantity":7,"name":"James Wilson","email":"sharon53@example.org","date":"2020-02-20"}
{"user_id":64,"product_id":88,"quantity":1,"name":"Elizabeth Murphy","email":"dbright@example.org","date":"2022-03-09"}
{"user_id":64,"product_id":90,"quantity":5,"name":"Elizabeth Murphy","email":"dbright@example.org","date":"2022-03-09"}
{"user_id":64,"product_id":75,"quantity":3,"name":"Elizabeth Murphy","email":"dbright@example.org","date":"2022-03-09"}
{"user_id":8,"product_id":36,"quantity":6,"name":"Aaron King","email":"marcusmerritt@example.org","date":"2020-02-28"}
{"user_id":72,"product_id":21,"quantity":2,"name":"Donald Hernandez","email":"jeffrey38@example.org","date":"2021-05-16"}
{"user_id":63,"product_id":53,"quantity":5,"name":"Gregory Munoz","email":"ericwilliams@example.org","date":"2020-08-10"}
{"user_id":43,"product_id":20,"quantity":6,"name":"Stephanie Anthony","email":"sarah57@example.com","date":"2021-05-09"}
{"user_id":50,"product_id":87,"quantity":9,"name":"Carolyn Carter","email":"valeriegoodman@example.net","date":"2022-02-28"}
{"user_id":24,"product_id":69,"quantity":5,"name":"Gary Henry","email":"mkidd@example.com","date":"2020-01-16"}
{"user_id":93,"product_id":21,"quantity":7,"name":"William Montgomery","email":"pateljoseph@example.com","date":"2021-03-23"}
{"user_id":98,"product_id":8,"quantity":7,"name":"Daniel Stuart","email":"hopkinskaren@example.net","date":"2021-10-25"}
{"user_id":33,"product_id":3,"quantity":2,"name":"Tanya Smith","email":"ylopez@example.com","date":"2020-04-16"}
{"user_id":56,"product_id":92,"quantity":6,"name":"Tyler Odonnell","email":"jeffrey91@example.com","date":"2022-01-19"}
{"user_id":65,"product_id":78,"quantity":6,"name":"Jay White","email":"marysmith@example.net","date":"2020-01-14"}
{"user_id":97,"product_id":73,"quantity":7,"name":"Justin Johnson","email":"graymatthew@example.org","date":"2021-05-22"}
{"user_id":57,"product_id":88,"quantity":5,"name":"Thomas Brown","email":"granttaylor@example.org","date":"2022-08-05"}
{"user_id":39,"product_id":74,"quantity":9,"name":"Amber Cross","email":"jeff98@example.com","date":"2021-05-21"}
{"user_id":15,"product_id":64,"quantity":1,"name":"Jeff Castillo","email":"jonathanmendoza@example.com","date":"2021-04-14"}
{"user_id":59,"product_id":98,"quantity":5,"name":"Russell Flores","email":"woodscameron@example.org","date":"2022-02-23"}
{"user_id":14,"product_id":53,"quantity":4,"name":"Nicholas Ashley","email":"wsmith@example.com","date":"2022-03-21"}
{"user_id":57,"product_id":34,"quantity":7,"name":"Thomas Brown","email":"granttaylor@example.org","date":"2022-08-05"}
{"user_id":62,"product_id":85,"quantity":3,"name":"Jeremiah Jordan","email":"lindseymartin@example.com","date":"2022-08-18"}
{"user_id":91,"product_id":59,"quantity":4,"name":"Brian Taylor","email":"william03@example.net","date":"2020-10-24"}
